cakap/__init__.py
cakap/base.py
cakap/decorators.py
cakap/filters.py
cakap/utils.py
cakap-0.5.0.dist-info/METADATA
cakap-0.5.0.dist-info/WHEEL
cakap-0.5.0.dist-info/top_level.txt
cakap-0.5.0.dist-info/RECORD
