Metadata-Version: 2.1
Name: cakap
Version: 0.5.0
Summary: UNKNOWN
Home-page: https://github.com/iomarmochtar/cakap
Author: Imam Omar Mochtar
Author-email: iomarmochtar@gmail.com
License: GPL
Keywords: Telegram bot framework
Platform: UNKNOWN
Requires-Dist: python-telegram-bot (==12.6.1)
Requires-Dist: colorlog (==4.0.2)
Requires-Dist: six (>=1.15.0)
